odoo/addons/stock_barcodes_picking_batch/README.rst
odoo/addons/stock_barcodes_picking_batch/__init__.py
odoo/addons/stock_barcodes_picking_batch/__manifest__.py
odoo/addons/stock_barcodes_picking_batch/data/stock_barcodes_action.xml
odoo/addons/stock_barcodes_picking_batch/i18n/es.po
odoo/addons/stock_barcodes_picking_batch/i18n/stock_barcodes_picking_batch.pot
odoo/addons/stock_barcodes_picking_batch/models/__init__.py
odoo/addons/stock_barcodes_picking_batch/models/stock_picking_batch.py
odoo/addons/stock_barcodes_picking_batch/readme/CONTRIBUTORS.rst
odoo/addons/stock_barcodes_picking_batch/readme/DESCRIPTION.rst
odoo/addons/stock_barcodes_picking_batch/readme/USAGE.rst
odoo/addons/stock_barcodes_picking_batch/static/description/icon.png
odoo/addons/stock_barcodes_picking_batch/static/description/index.html
odoo/addons/stock_barcodes_picking_batch/static/src/js/barcodes_models_mixin.js
odoo/addons/stock_barcodes_picking_batch/views/assets.xml
odoo/addons/stock_barcodes_picking_batch/views/stock_picking_batch_views.xml
odoo/addons/stock_barcodes_picking_batch/wizard/__init__.py
odoo/addons/stock_barcodes_picking_batch/wizard/stock_barcodes_read_picking_batch.py
odoo/addons/stock_barcodes_picking_batch/wizard/stock_barcodes_read_picking_batch_views.xml
odoo13_addon_stock_barcodes_picking_batch-13.0.1.0.1.dev4.dist-info/METADATA
odoo13_addon_stock_barcodes_picking_batch-13.0.1.0.1.dev4.dist-info/WHEEL
odoo13_addon_stock_barcodes_picking_batch-13.0.1.0.1.dev4.dist-info/top_level.txt
odoo13_addon_stock_barcodes_picking_batch-13.0.1.0.1.dev4.dist-info/RECORD
