Metadata-Version: 2.1
Name: odoo13-addon-stock-barcodes-picking-batch
Version: 13.0.1.0.1.dev4
Summary: It provides read barcodes on stock operations from batch pickings.
Home-page: https://github.com/OCA/stock-logistics-barcode
Author: Tecnativa, Odoo Community Association (OCA)
Author-email: support@odoo-community.org
License: AGPL-3
Platform: UNKNOWN
Classifier: Programming Language :: Python
Classifier: Framework :: Odoo
Classifier: Framework :: Odoo :: 13.0
Classifier: License :: OSI Approved :: GNU Affero General Public License v3
Requires-Python: >=3.5
Requires-Dist: odoo13-addon-stock-barcodes
Requires-Dist: odoo13-addon-stock-picking-batch-extended
Requires-Dist: odoo <13.1dev,>=13.0a
